CHANGES.md
MANIFEST.in
README.md
setup.py
bin/silp
silp/__init__.py
silp/language.py
silp/processor.py
silp/rule.py
silp/setting.py
silp/silp.py
silp/term.py
silp.egg-info/PKG-INFO
silp.egg-info/SOURCES.txt
silp.egg-info/dependency_links.txt
silp.egg-info/requires.txt
silp.egg-info/top_level.txt