Metadata-Version: 1.1
Name: silp
Version: 0.3.6
Summary: Simple Individual Line Preprocessor
Home-page: http://github.com/yjpark/silp/
Author: YJ Park
Author-email: yjpark@gmail.com
License: MIT License
Platform: any
Classifier: Programming Language :: Python
Classifier: Development Status :: 4 - Beta
Classifier: Natural Language :: English
Classifier: Intended Audience :: Developers
Classifier: License :: OSI Approved :: MIT License
Classifier: Operating System :: OS Independent
Classifier: Topic :: Software Development :: Libraries :: Python Modules
